kattiskitten/__init__.py
kattiskitten/config.py
kattiskitten/language_detector.py
kattiskitten/languages/c++.py
kattiskitten/languages/c.py
kattiskitten/languages/java.py
kattiskitten/languages/python3.py
kattiskitten/languages/rust.py
kattiskitten/submitter.py
kattiskitten/tester.py
kattiskitten-0.14.0.dist-info/entry_points.txt
kattiskitten-0.14.0.dist-info/LICENSE
kattiskitten-0.14.0.dist-info/WHEEL
kattiskitten-0.14.0.dist-info/METADATA
kattiskitten-0.14.0.dist-info/RECORD
