Metadata-Version: 2.1
Name: kattiskitten
Version: 0.14.0
Summary: Kattis CLI - Easily download, test and submit kattis problems
Home-page: https://github.com/FelixDQ/kattis-kitten
License: MIT
Author: Felix Qvist
Author-email: felix@qvist.dev
Requires-Python: >=3.6,<4.0
Classifier: License :: OSI Approved :: MIT License
Classifier: Programming Language :: Python :: 3
Classifier: Programming Language :: Python :: 3.6
Classifier: Programming Language :: Python :: 3.7
Classifier: Programming Language :: Python :: 3.8
Classifier: Programming Language :: Python :: 3.9
Requires-Dist: click (==7.0)
Requires-Dist: colorful (==0.5.4)
Requires-Dist: requests (==2.22.0)
Project-URL: Repository, https://github.com/FelixDQ/kattis-kitten
